zd/__init__.py
zd-0.0.4.data/scripts/zdcat
zd-0.0.4.dist-info/LICENSE
zd-0.0.4.dist-info/METADATA
zd-0.0.4.dist-info/WHEEL
zd-0.0.4.dist-info/top_level.txt
zd-0.0.4.dist-info/zip-safe
zd-0.0.4.dist-info/RECORD
