Metadata-Version: 2.1
Name: zd
Version: 0.0.4
Summary: file like object for zstandard
Home-page: https://gitee.com/znlp/zd
Author: zuroc
Author-email: zsp042@gmail.com
License: UNKNOWN
Platform: UNKNOWN
Requires-Dist: fire
Requires-Dist: zstandard
